tik4free/__init__.py
tik4free/base.py
tiktools-1.0.0.dist-info/METADATA
tiktools-1.0.0.dist-info/WHEEL
tiktools-1.0.0.dist-info/top_level.txt
tiktools-1.0.0.dist-info/RECORD
