Metadata-Version: 2.1
Name: tiktools
Version: 1.0.0
Summary: Some Usefull Tools for Tiktok!
Author: vardxg
Author-email: <dev@vardxg.lol>
Keywords: python,dev,free,tiktok,tools
Classifier: Development Status :: 1 - Planning
Classifier: Intended Audience :: Developers
Classifier: Programming Language :: Python :: 3
Classifier: Operating System :: Unix
Classifier: Operating System :: MacOS :: MacOS X
Classifier: Operating System :: Microsoft :: Windows
Requires-Dist: requests
